MANIFEST.in
NEWS.txt
README.rst
setup.py
applib/__init__.py
applib/_cmdln.py
applib/_compression.py
applib/_proc.py
applib/_simpledb.py
applib/base.py
applib/location.py
applib/log.py
applib/misc.py
applib/sh.py
applib/textui.py
applib.egg-info/PKG-INFO
applib.egg-info/SOURCES.txt
applib.egg-info/dependency_links.txt
applib.egg-info/entry_points.txt
applib.egg-info/top_level.txt
applib.egg-info/zip-safe