Metadata-Version: 1.0
Name: applib
Version: 1.0.1
Summary: Cross-platform application utilities in Python
Home-page: http://github.com/ActiveState/applib
Author: Sridhar Ratnakumar
Author-email: sridhar.ratna@gmail.com
License: MIT
Platform: UNKNOWN
Classifier: Development Status :: 5 - Production/Stable
Classifier: Intended Audience :: Developers
Classifier: License :: OSI Approved :: MIT License
Classifier: Operating System :: OS Independent
Classifier: Programming Language :: Python :: 2.6
Classifier: Programming Language :: Python :: 2.7
Classifier: Programming Language :: Python :: 3
Classifier: Topic :: Software Development :: Libraries :: Python Modules
Classifier: Topic :: Utilities
